attribute_mapping.py
attribute_mapping-1.3.0.dist-info/LICENSE.rst
attribute_mapping-1.3.0.dist-info/METADATA
attribute_mapping-1.3.0.dist-info/WHEEL
attribute_mapping-1.3.0.dist-info/top_level.txt
attribute_mapping-1.3.0.dist-info/RECORD
