Metadata-Version: 2.1
Name: attribute-mapping
Version: 1.3.0
Summary: minimalistic library for attribute-based access to dictionaries and other mappings
Home-page: https://github.com/wbolster/attribute-mapping
Author: wouter bolsterlee
Author-email: wouter@bolsterl.ee
License: BSD
Platform: UNKNOWN
Classifier: Development Status :: 5 - Production/Stable
Classifier: License :: OSI Approved :: BSD License
Classifier: Programming Language :: Python
Classifier: Programming Language :: Python :: 3
Classifier: Topic :: Software Development :: Libraries
Classifier: Topic :: Software Development :: Libraries :: Python Modules
